<?xml version="1.0"  encoding="UTF-8"?><categories><category><![CDATA[amateur]]></category><category><![CDATA[anal]]></category><category><![CDATA[asian]]></category><category><![CDATA[bigtits]]></category><category><![CDATA[blonde]]></category><category><![CDATA[blowjob]]></category><category><![CDATA[creampie]]></category><category><![CDATA[cumshot]]></category><category><![CDATA[doublepenetration]]></category><category><![CDATA[ebony]]></category><category><![CDATA[facials]]></category><category><![CDATA[fetish]]></category><category><![CDATA[gangbang]]></category><category><![CDATA[gay]]></category><category><![CDATA[group]]></category><category><![CDATA[hentai]]></category><category><![CDATA[interracial]]></category><category><![CDATA[japanese]]></category><category><![CDATA[latina]]></category><category><![CDATA[lesbian]]></category><category><![CDATA[lingerie]]></category><category><![CDATA[masturbation]]></category><category><![CDATA[mature]]></category><category><![CDATA[milf]]></category><category><![CDATA[pov]]></category><category><![CDATA[public]]></category><category><![CDATA[redhead]]></category><category><![CDATA[shemale]]></category><category><![CDATA[squirting]]></category><category><![CDATA[teens]]></category><category><![CDATA[vintage]]></category><category><![CDATA[wildcrazy]]></category></categories>